[
  {
    "ID": 1,
    "urban": "宁波市",
    "district": "慈溪市",
    "year_2018": 61,
    "year_2017": 65,
    "year_2016": 70,
    "year_2015": 70,
    "year_2014": 101,
    "year_2013": 147,
    "year_2012": 146,
    "year_2011": 169,
    "year_2010": 195,
    "year_2009": 191,
    "year_2008": 187,
    "year_2007": 211,
    "year_2006": 194,
    "year_2005": 248,
    "year_2004": 241,
    "year_2003": 289,
    "year_2002": 334,
    "year_2001": 354
  },
  {
    "ID": 2,
    "urban": "宁波市",
    "district": "余姚市",
    "year_2018": 4014,
    "year_2017": 4300,
    "year_2016": 4796,
    "year_2015": 4826,
    "year_2014": 4829,
    "year_2013": 4267,
    "year_2012": 4745,
    "year_2011": 5513,
    "year_2010": 5313,
    "year_2009": 5449,
    "year_2008": 5979,
    "year_2007": 6259,
    "year_2006": 6859,
    "year_2005": 6000,
    "year_2004": 5600,
    "year_2003": 5500,
    "year_2002": 5378,
    "year_2001": 5000
  },
  {
    "ID": 3,
    "urban": "宁波市",
    "district": "海曙区",
    "year_2018": "-",
    "year_2017": "-",
    "year_2016": "-",
    "year_2015": "-",
    "year_2014": "-",
    "year_2013": "-",
    "year_2012": "-",
    "year_2011": "-",
    "year_2010": "-",
    "year_2009": "-",
    "year_2008": "-",
    "year_2007": "-",
    "year_2006": "-",
    "year_2005": "-",
    "year_2004": "-",
    "year_2003": "-",
    "year_2002": "-",
    "year_2001": "-"
  },
  {
    "ID": 4,
    "urban": "宁波市",
    "district": "奉化区",
    "year_2018": 1062,
    "year_2017": 1177,
    "year_2016": 1202,
    "year_2015": 1242,
    "year_2014": 1436,
    "year_2013": 1321,
    "year_2012": 1277,
    "year_2011": 1493,
    "year_2010": 1551,
    "year_2009": 1640,
    "year_2008": 2137,
    "year_2007": 2332,
    "year_2006": 2369,
    "year_2005": 2276,
    "year_2004": 1972,
    "year_2003": 1945,
    "year_2002": 1971,
    "year_2001": 2607
  },
  {
    "ID": 5,
    "urban": "宁波市",
    "district": "北仑区",
    "year_2018": 416,
    "year_2017": 436,
    "year_2016": 425,
    "year_2015": 449,
    "year_2014": 510,
    "year_2013": 588,
    "year_2012": 492,
    "year_2011": 592,
    "year_2010": 576,
    "year_2009": 630,
    "year_2008": 791,
    "year_2007": 1761,
    "year_2006": 1806,
    "year_2005": 1820,
    "year_2004": 2102,
    "year_2003": 2214,
    "year_2002": 2379,
    "year_2001": 2177
  },
  {
    "ID": 6,
    "urban": "宁波市",
    "district": "江北区",
    "year_2018": 62,
    "year_2017": 64,
    "year_2016": 62,
    "year_2015": 61,
    "year_2014": 90,
    "year_2013": 102,
    "year_2012": 94,
    "year_2011": 105,
    "year_2010": 94,
    "year_2009": 106,
    "year_2008": 158,
    "year_2007": 208,
    "year_2006": 212,
    "year_2005": 236,
    "year_2004": 264,
    "year_2003": 332,
    "year_2002": 358,
    "year_2001": 296
  },
  {
    "ID": 7,
    "urban": "宁波市",
    "district": "镇海区",
    "year_2018": 94,
    "year_2017": 85,
    "year_2016": 99,
    "year_2015": 107,
    "year_2014": 127,
    "year_2013": 130,
    "year_2012": 170,
    "year_2011": 195,
    "year_2010": 212,
    "year_2009": 193,
    "year_2008": 185,
    "year_2007": 186,
    "year_2006": 185,
    "year_2005": 194,
    "year_2004": 140,
    "year_2003": 104,
    "year_2002": 91,
    "year_2001": 111
  },
  {
    "ID": 8,
    "urban": "宁波市",
    "district": "象山县",
    "year_2018": 588,
    "year_2017": 710,
    "year_2016": 930,
    "year_2015": 947,
    "year_2014": 1254,
    "year_2013": 1269,
    "year_2012": 1510,
    "year_2011": 1605,
    "year_2010": 1550,
    "year_2009": 1438,
    "year_2008": 1365,
    "year_2007": 1480,
    "year_2006": 1525,
    "year_2005": 1485,
    "year_2004": 1450,
    "year_2003": 1431,
    "year_2002": 1457,
    "year_2001": 1558
  },
  {
    "ID": 9,
    "urban": "宁波市",
    "district": "宁海县",
    "year_2018": 4646,
    "year_2017": 4653,
    "year_2016": 4513,
    "year_2015": 4736,
    "year_2014": 4774,
    "year_2013": 4799,
    "year_2012": 5317,
    "year_2011": 5246,
    "year_2010": 5680,
    "year_2009": 6049,
    "year_2008": 6167,
    "year_2007": 7098,
    "year_2006": 6255,
    "year_2005": 6493,
    "year_2004": 5723,
    "year_2003": 5120,
    "year_2002": 4785,
    "year_2001": 4436
  },
  {
    "ID": 10,
    "urban": "宁波市",
    "district": "鄞州区",
    "year_2018": 2204,
    "year_2017": 2109,
    "year_2016": 2126,
    "year_2015": 2058,
    "year_2014": 2800,
    "year_2013": 2654,
    "year_2012": 2853,
    "year_2011": 2925,
    "year_2010": 2984,
    "year_2009": 3106,
    "year_2008": 3316,
    "year_2007": 3193,
    "year_2006": 2779,
    "year_2005": 2659,
    "year_2004": 2444,
    "year_2003": 2219,
    "year_2002": 2220,
    "year_2001": 2285
  },
  {
    "ID": 11,
    "urban": "宁波市",
    "district": "宁波市",
    "year_2018": 13147,
    "year_2017": 13599,
    "year_2016": 14223,
    "year_2015": 14496,
    "year_2014": 15921,
    "year_2013": 15277,
    "year_2012": 16604,
    "year_2011": 17843,
    "year_2010": 18155,
    "year_2009": 18802,
    "year_2008": 20285,
    "year_2007": 22728,
    "year_2006": 22184,
    "year_2005": 21411,
    "year_2004": 19936,
    "year_2003": 19154,
    "year_2002": 18973,
    "year_2001": 18824
  },
  {
    "ID": 12,
    "urban": "台州市",
    "district": "黄岩区",
    "year_2018": 50,
    "year_2017": 54,
    "year_2016": 53,
    "year_2015": 48,
    "year_2014": 49,
    "year_2013": 48,
    "year_2012": 52,
    "year_2011": 55,
    "year_2010": 58,
    "year_2009": 58,
    "year_2008": 60,
    "year_2007": 61,
    "year_2006": 69,
    "year_2005": 68,
    "year_2004": 73,
    "year_2003": 87,
    "year_2002": 98,
    "year_2001": 121
  },
  {
    "ID": 13,
    "urban": "台州市",
    "district": "椒江区",
    "year_2018": "-",
    "year_2017": "-",
    "year_2016": "-",
    "year_2015": "-",
    "year_2014": "-",
    "year_2013": "-",
    "year_2012": "-",
    "year_2011": "-",
    "year_2010": "-",
    "year_2009": "-",
    "year_2008": "-",
    "year_2007": "-",
    "year_2006": "-",
    "year_2005": "-",
    "year_2004": "-",
    "year_2003": "-",
    "year_2002": "-",
    "year_2001": "-"
  },
  {
    "ID": 14,
    "urban": "台州市",
    "district": "路桥区",
    "year_2018": "-",
    "year_2017": "-",
    "year_2016": "-",
    "year_2015": "-",
    "year_2014": "-",
    "year_2013": "-",
    "year_2012": "-",
    "year_2011": "-",
    "year_2010": "-",
    "year_2009": "-",
    "year_2008": "-",
    "year_2007": "-",
    "year_2006": "-",
    "year_2005": "-",
    "year_2004": "-",
    "year_2003": "-",
    "year_2002": "-",
    "year_2001": "-"
  },
  {
    "ID": 15,
    "urban": "台州市",
    "district": "仙居县",
    "year_2018": 474,
    "year_2017": 500,
    "year_2016": 500,
    "year_2015": 498,
    "year_2014": 496,
    "year_2013": 509,
    "year_2012": 638,
    "year_2011": 617,
    "year_2010": 587,
    "year_2009": 591,
    "year_2008": 560,
    "year_2007": 544,
    "year_2006": 497,
    "year_2005": 471,
    "year_2004": 471,
    "year_2003": 511,
    "year_2002": 504,
    "year_2001": 515
  },
  {
    "ID": 16,
    "urban": "台州市",
    "district": "玉环市",
    "year_2018": 9,
    "year_2017": 10,
    "year_2016": 9,
    "year_2015": 7,
    "year_2014": 7,
    "year_2013": 13,
    "year_2012": 6,
    "year_2011": 5,
    "year_2010": "-",
    "year_2009": 5,
    "year_2008": 5,
    "year_2007": 43,
    "year_2006": 50,
    "year_2005": 45,
    "year_2004": 45,
    "year_2003": 40,
    "year_2002": 18,
    "year_2001": 5
  },
  {
    "ID": 17,
    "urban": "台州市",
    "district": "临海市",
    "year_2018": 1228,
    "year_2017": 1203,
    "year_2016": 1096,
    "year_2015": 1081,
    "year_2014": 1003,
    "year_2013": 1000,
    "year_2012": 1015,
    "year_2011": 1009,
    "year_2010": 941,
    "year_2009": 800,
    "year_2008": 725,
    "year_2007": 705,
    "year_2006": 701,
    "year_2005": 689,
    "year_2004": 704,
    "year_2003": 1041,
    "year_2002": 933,
    "year_2001": 925
  },
  {
    "ID": 18,
    "urban": "台州市",
    "district": "天台县",
    "year_2018": 2710,
    "year_2017": 2644,
    "year_2016": 2544,
    "year_2015": 2375,
    "year_2014": 2423,
    "year_2013": 2295,
    "year_2012": 2060,
    "year_2011": 1974,
    "year_2010": 1750,
    "year_2009": 1900,
    "year_2008": 1573,
    "year_2007": 1370,
    "year_2006": 1200,
    "year_2005": 1053,
    "year_2004": 1011,
    "year_2003": 900,
    "year_2002": 876,
    "year_2001": 864
  },
  {
    "ID": 19,
    "urban": "台州市",
    "district": "三门县",
    "year_2018": 739,
    "year_2017": 747,
    "year_2016": 723,
    "year_2015": 698,
    "year_2014": 700,
    "year_2013": 695,
    "year_2012": 706,
    "year_2011": 688,
    "year_2010": 683,
    "year_2009": 743,
    "year_2008": 787,
    "year_2007": 781,
    "year_2006": 770,
    "year_2005": 750,
    "year_2004": 669,
    "year_2003": 660,
    "year_2002": 603,
    "year_2001": 539
  },
  {
    "ID": 20,
    "urban": "台州市",
    "district": "温岭市",
    "year_2018": 75,
    "year_2017": 78,
    "year_2016": 76,
    "year_2015": 57,
    "year_2014": 45,
    "year_2013": 49,
    "year_2012": 49,
    "year_2011": 50,
    "year_2010": 47,
    "year_2009": 62,
    "year_2008": 68,
    "year_2007": 68,
    "year_2006": 68,
    "year_2005": 67,
    "year_2004": 63,
    "year_2003": 58,
    "year_2002": 60,
    "year_2001": 50
  },
  {
    "ID": 21,
    "urban": "台州市",
    "district": "台州市",
    "year_2018": 5285,
    "year_2017": 5236,
    "year_2016": 5001,
    "year_2015": 4764,
    "year_2014": 4723,
    "year_2013": 4609,
    "year_2012": 4526,
    "year_2011": 4398,
    "year_2010": 4066,
    "year_2009": 4159,
    "year_2008": 3778,
    "year_2007": 3572,
    "year_2006": 3355,
    "year_2005": 3143,
    "year_2004": 3036,
    "year_2003": 3297,
    "year_2002": 3092,
    "year_2001": 3019
  },
  {
    "ID": 22,
    "urban": "嘉兴市",
    "district": "南湖区",
    "year_2018": "-",
    "year_2017": "-",
    "year_2016": "-",
    "year_2015": "-",
    "year_2014": "-",
    "year_2013": "-",
    "year_2012": "-",
    "year_2011": "-",
    "year_2010": "-",
    "year_2009": "-",
    "year_2008": "-",
    "year_2007": "-",
    "year_2006": "-",
    "year_2005": "-",
    "year_2004": "-",
    "year_2003": "-",
    "year_2002": "-",
    "year_2001": "-"
  },
  {
    "ID": 23,
    "urban": "嘉兴市",
    "district": "嘉善县",
    "year_2018": "-",
    "year_2017": "-",
    "year_2016": "-",
    "year_2015": "-",
    "year_2014": "-",
    "year_2013": "-",
    "year_2012": "-",
    "year_2011": "-",
    "year_2010": "-",
    "year_2009": "-",
    "year_2008": "-",
    "year_2007": "-",
    "year_2006": "-",
    "year_2005": "-",
    "year_2004": "-",
    "year_2003": "-",
    "year_2002": "-",
    "year_2001": "-"
  },
  {
    "ID": 24,
    "urban": "嘉兴市",
    "district": "海宁市",
    "year_2018": "-",
    "year_2017": "-",
    "year_2016": "-",
    "year_2015": "-",
    "year_2014": "-",
    "year_2013": "-",
    "year_2012": "-",
    "year_2011": "-",
    "year_2010": "-",
    "year_2009": "-",
    "year_2008": "-",
    "year_2007": "-",
    "year_2006": "-",
    "year_2005": "-",
    "year_2004": "-",
    "year_2003": "-",
    "year_2002": "-",
    "year_2001": "-"
  },
  {
    "ID": 25,
    "urban": "嘉兴市",
    "district": "平湖市",
    "year_2018": "-",
    "year_2017": "-",
    "year_2016": "-",
    "year_2015": "-",
    "year_2014": "-",
    "year_2013": "-",
    "year_2012": "-",
    "year_2011": "-",
    "year_2010": "-",
    "year_2009": "-",
    "year_2008": "-",
    "year_2007": "-",
    "year_2006": "-",
    "year_2005": "-",
    "year_2004": "-",
    "year_2003": "-",
    "year_2002": "-",
    "year_2001": "-"
  },
  {
    "ID": 26,
    "urban": "嘉兴市",
    "district": "桐乡市",
    "year_2018": "-",
    "year_2017": "-",
    "year_2016": "-",
    "year_2015": "-",
    "year_2014": "-",
    "year_2013": "-",
    "year_2012": "-",
    "year_2011": "-",
    "year_2010": "-",
    "year_2009": "-",
    "year_2008": "-",
    "year_2007": "-",
    "year_2006": "-",
    "year_2005": "-",
    "year_2004": "-",
    "year_2003": "-",
    "year_2002": "-",
    "year_2001": "-"
  },
  {
    "ID": 27,
    "urban": "嘉兴市",
    "district": "秀洲区",
    "year_2018": "-",
    "year_2017": "-",
    "year_2016": "-",
    "year_2015": "-",
    "year_2014": "-",
    "year_2013": "-",
    "year_2012": "-",
    "year_2011": "-",
    "year_2010": "-",
    "year_2009": "-",
    "year_2008": "-",
    "year_2007": "-",
    "year_2006": "-",
    "year_2005": "-",
    "year_2004": "-",
    "year_2003": "-",
    "year_2002": "-",
    "year_2001": "-"
  },
  {
    "ID": 28,
    "urban": "嘉兴市",
    "district": "海盐县",
    "year_2018": "-",
    "year_2017": "-",
    "year_2016": "-",
    "year_2015": "-",
    "year_2014": "-",
    "year_2013": "-",
    "year_2012": "-",
    "year_2011": "-",
    "year_2010": "-",
    "year_2009": "-",
    "year_2008": "-",
    "year_2007": "-",
    "year_2006": "-",
    "year_2005": "-",
    "year_2004": "-",
    "year_2003": "-",
    "year_2002": "-",
    "year_2001": "-"
  },
  {
    "ID": 29,
    "urban": "嘉兴市",
    "district": "嘉兴市",
    "year_2018": "-",
    "year_2017": "-",
    "year_2016": "-",
    "year_2015": "-",
    "year_2014": "-",
    "year_2013": "-",
    "year_2012": "-",
    "year_2011": "-",
    "year_2010": "-",
    "year_2009": "-",
    "year_2008": "-",
    "year_2007": "-",
    "year_2006": "-",
    "year_2005": "-",
    "year_2004": "-",
    "year_2003": "-",
    "year_2002": "-",
    "year_2001": "-"
  },
  {
    "ID": 30,
    "urban": "舟山市",
    "district": "嵊泗县",
    "year_2018": "-",
    "year_2017": "-",
    "year_2016": "-",
    "year_2015": "-",
    "year_2014": "-",
    "year_2013": "-",
    "year_2012": "-",
    "year_2011": "-",
    "year_2010": "-",
    "year_2009": "-",
    "year_2008": "-",
    "year_2007": "-",
    "year_2006": "-",
    "year_2005": "-",
    "year_2004": "-",
    "year_2003": "-",
    "year_2002": "-",
    "year_2001": "-"
  },
  {
    "ID": 31,
    "urban": "舟山市",
    "district": "岱山县",
    "year_2018": "-",
    "year_2017": "-",
    "year_2016": "-",
    "year_2015": "-",
    "year_2014": "-",
    "year_2013": "-",
    "year_2012": "-",
    "year_2011": "-",
    "year_2010": "-",
    "year_2009": "-",
    "year_2008": "-",
    "year_2007": "-",
    "year_2006": "-",
    "year_2005": "-",
    "year_2004": "-",
    "year_2003": "-",
    "year_2002": "-",
    "year_2001": "-"
  },
  {
    "ID": 32,
    "urban": "舟山市",
    "district": "普陀区",
    "year_2018": "-",
    "year_2017": "-",
    "year_2016": "-",
    "year_2015": "-",
    "year_2014": "-",
    "year_2013": "-",
    "year_2012": "-",
    "year_2011": "-",
    "year_2010": "-",
    "year_2009": "-",
    "year_2008": "-",
    "year_2007": "-",
    "year_2006": "-",
    "year_2005": "-",
    "year_2004": "-",
    "year_2003": "-",
    "year_2002": "-",
    "year_2001": "-"
  },
  {
    "ID": 33,
    "urban": "舟山市",
    "district": "定海区",
    "year_2018": "-",
    "year_2017": "-",
    "year_2016": "-",
    "year_2015": "-",
    "year_2014": "-",
    "year_2013": "-",
    "year_2012": "-",
    "year_2011": "-",
    "year_2010": "-",
    "year_2009": "-",
    "year_2008": "-",
    "year_2007": "-",
    "year_2006": "-",
    "year_2005": "-",
    "year_2004": "-",
    "year_2003": "-",
    "year_2002": "-",
    "year_2001": "-"
  },
  {
    "ID": 34,
    "urban": "舟山市",
    "district": "舟山市",
    "year_2018": "-",
    "year_2017": "-",
    "year_2016": "-",
    "year_2015": "-",
    "year_2014": "-",
    "year_2013": "-",
    "year_2012": "-",
    "year_2011": "-",
    "year_2010": "-",
    "year_2009": "-",
    "year_2008": "-",
    "year_2007": "-",
    "year_2006": "-",
    "year_2005": "-",
    "year_2004": "-",
    "year_2003": "-",
    "year_2002": "-",
    "year_2001": "-"
  },
  {
    "ID": 35,
    "urban": "温州市",
    "district": "洞头区",
    "year_2018": "-",
    "year_2017": "-",
    "year_2016": "-",
    "year_2015": "-",
    "year_2014": "-",
    "year_2013": "-",
    "year_2012": "-",
    "year_2011": "-",
    "year_2010": "-",
    "year_2009": "-",
    "year_2008": "-",
    "year_2007": "-",
    "year_2006": "-",
    "year_2005": "-",
    "year_2004": "-",
    "year_2003": "-",
    "year_2002": "-",
    "year_2001": "-"
  },
  {
    "ID": 36,
    "urban": "温州市",
    "district": "瓯海区",
    "year_2018": 39,
    "year_2017": 39,
    "year_2016": 41,
    "year_2015": 46,
    "year_2014": 36,
    "year_2013": 35,
    "year_2012": 34,
    "year_2011": 25,
    "year_2010": 17,
    "year_2009": 32,
    "year_2008": 29,
    "year_2007": 32,
    "year_2006": 37,
    "year_2005": 43,
    "year_2004": 51,
    "year_2003": 60,
    "year_2002": 56,
    "year_2001": 59
  },
  {
    "ID": 37,
    "urban": "温州市",
    "district": "龙湾区",
    "year_2018": "-",
    "year_2017": "-",
    "year_2016": "-",
    "year_2015": "-",
    "year_2014": "-",
    "year_2013": "-",
    "year_2012": "-",
    "year_2011": "-",
    "year_2010": "-",
    "year_2009": "-",
    "year_2008": "-",
    "year_2007": "-",
    "year_2006": "-",
    "year_2005": "-",
    "year_2004": "-",
    "year_2003": "-",
    "year_2002": "-",
    "year_2001": "-"
  },
  {
    "ID": 38,
    "urban": "温州市",
    "district": "鹿城区",
    "year_2018": 2,
    "year_2017": 2,
    "year_2016": 2,
    "year_2015": 1,
    "year_2014": 1,
    "year_2013": 2,
    "year_2012": 2,
    "year_2011": 2,
    "year_2010": 1,
    "year_2009": 2,
    "year_2008": 2,
    "year_2007": 1,
    "year_2006": 1,
    "year_2005": 3,
    "year_2004": 4,
    "year_2003": 5,
    "year_2002": 4,
    "year_2001": 7
  },
  {
    "ID": 39,
    "urban": "温州市",
    "district": "乐清市",
    "year_2018": 161,
    "year_2017": 154,
    "year_2016": 155,
    "year_2015": 157,
    "year_2014": 155,
    "year_2013": 152,
    "year_2012": 170,
    "year_2011": 158,
    "year_2010": 152,
    "year_2009": 212,
    "year_2008": 178,
    "year_2007": 150,
    "year_2006": 119,
    "year_2005": 116,
    "year_2004": 116,
    "year_2003": 101,
    "year_2002": 56,
    "year_2001": 91
  },
  {
    "ID": 40,
    "urban": "温州市",
    "district": "瑞安市",
    "year_2018": 81,
    "year_2017": 82,
    "year_2016": 86,
    "year_2015": 78,
    "year_2014": 77,
    "year_2013": 70,
    "year_2012": 68,
    "year_2011": 86,
    "year_2010": 76,
    "year_2009": 79,
    "year_2008": 80,
    "year_2007": 55,
    "year_2006": 64,
    "year_2005": 75,
    "year_2004": 87,
    "year_2003": 66,
    "year_2002": 70,
    "year_2001": 79
  },
  {
    "ID": 41,
    "urban": "温州市",
    "district": "泰顺县",
    "year_2018": 3461,
    "year_2017": 3376,
    "year_2016": 3229,
    "year_2015": 3049,
    "year_2014": 2793,
    "year_2013": 2618,
    "year_2012": 2496,
    "year_2011": 2463,
    "year_2010": 2303,
    "year_2009": 2166,
    "year_2008": 2163,
    "year_2007": 1914,
    "year_2006": 1350,
    "year_2005": 1295,
    "year_2004": 1366,
    "year_2003": 1324,
    "year_2002": 1405,
    "year_2001": 1271
  },
  {
    "ID": 42,
    "urban": "温州市",
    "district": "文成县",
    "year_2018": 474,
    "year_2017": 431,
    "year_2016": 408,
    "year_2015": 390,
    "year_2014": 370,
    "year_2013": 275,
    "year_2012": 268,
    "year_2011": 228,
    "year_2010": 174,
    "year_2009": 175,
    "year_2008": 160,
    "year_2007": 144,
    "year_2006": 152,
    "year_2005": 152,
    "year_2004": 155,
    "year_2003": 142,
    "year_2002": 129,
    "year_2001": 110
  },
  {
    "ID": 43,
    "urban": "温州市",
    "district": "永嘉县",
    "year_2018": 706,
    "year_2017": 649,
    "year_2016": 601,
    "year_2015": 673,
    "year_2014": 668,
    "year_2013": 594,
    "year_2012": 628,
    "year_2011": 614,
    "year_2010": 414,
    "year_2009": 540,
    "year_2008": 472,
    "year_2007": 472,
    "year_2006": 419,
    "year_2005": 350,
    "year_2004": 384,
    "year_2003": 370,
    "year_2002": 286,
    "year_2001": 256
  },
  {
    "ID": 44,
    "urban": "温州市",
    "district": "苍南县",
    "year_2018": 942,
    "year_2017": 878,
    "year_2016": 800,
    "year_2015": 801,
    "year_2014": 725,
    "year_2013": 787,
    "year_2012": 773,
    "year_2011": 679,
    "year_2010": 709,
    "year_2009": 696,
    "year_2008": 652,
    "year_2007": 621,
    "year_2006": 681,
    "year_2005": 700,
    "year_2004": 680,
    "year_2003": 689,
    "year_2002": 704,
    "year_2001": 703
  },
  {
    "ID": 45,
    "urban": "温州市",
    "district": "平阳县",
    "year_2018": 969,
    "year_2017": 836,
    "year_2016": 772,
    "year_2015": 688,
    "year_2014": 639,
    "year_2013": 584,
    "year_2012": 534,
    "year_2011": 581,
    "year_2010": 714,
    "year_2009": 737,
    "year_2008": 700,
    "year_2007": 633,
    "year_2006": 601,
    "year_2005": 383,
    "year_2004": 363,
    "year_2003": 346,
    "year_2002": 343,
    "year_2001": 287
  },
  {
    "ID": 46,
    "urban": "温州市",
    "district": "温州市",
    "year_2018": 6835,
    "year_2017": 6447,
    "year_2016": 6094,
    "year_2015": 5883,
    "year_2014": 5464,
    "year_2013": 5117,
    "year_2012": 4973,
    "year_2011": 4836,
    "year_2010": 4560,
    "year_2009": 4639,
    "year_2008": 4436,
    "year_2007": 4022,
    "year_2006": 3424,
    "year_2005": 3117,
    "year_2004": 3206,
    "year_2003": 3103,
    "year_2002": 3053,
    "year_2001": 2863
  },
  {
    "ID": 47,
    "urban": "衢州市",
    "district": "柯城区",
    "year_2018": 59,
    "year_2017": 60,
    "year_2016": 66,
    "year_2015": 69,
    "year_2014": 64,
    "year_2013": 64,
    "year_2012": 67,
    "year_2011": 65,
    "year_2010": 47,
    "year_2009": 54,
    "year_2008": 47,
    "year_2007": 42,
    "year_2006": 42,
    "year_2005": 48,
    "year_2004": 51,
    "year_2003": 41,
    "year_2002": "-",
    "year_2001": "-"
  },
  {
    "ID": 48,
    "urban": "衢州市",
    "district": "衢江区",
    "year_2018": 1353,
    "year_2017": 1319,
    "year_2016": 1210,
    "year_2015": 1184,
    "year_2014": 1116,
    "year_2013": 740,
    "year_2012": 747,
    "year_2011": 683,
    "year_2010": 653,
    "year_2009": 660,
    "year_2008": 578,
    "year_2007": 607,
    "year_2006": 540,
    "year_2005": 511,
    "year_2004": 452,
    "year_2003": 421,
    "year_2002": "-",
    "year_2001": "-"
  },
  {
    "ID": 49,
    "urban": "衢州市",
    "district": "常山县",
    "year_2018": 218,
    "year_2017": 216,
    "year_2016": 215,
    "year_2015": 207,
    "year_2014": 127,
    "year_2013": 117,
    "year_2012": 121,
    "year_2011": 117,
    "year_2010": 116,
    "year_2009": 116,
    "year_2008": 122,
    "year_2007": 131,
    "year_2006": 131,
    "year_2005": 140,
    "year_2004": 37,
    "year_2003": 164,
    "year_2002": "-",
    "year_2001": "-"
  },
  {
    "ID": 50,
    "urban": "衢州市",
    "district": "江山市",
    "year_2018": 1479,
    "year_2017": 1444,
    "year_2016": 1422,
    "year_2015": 1409,
    "year_2014": 1366,
    "year_2013": 1311,
    "year_2012": 1317,
    "year_2011": 1217,
    "year_2010": 1163,
    "year_2009": 2052,
    "year_2008": 2026,
    "year_2007": 1889,
    "year_2006": 1891,
    "year_2005": 1701,
    "year_2004": 264,
    "year_2003": 1570,
    "year_2002": "-",
    "year_2001": "-"
  },
  {
    "ID": 51,
    "urban": "衢州市",
    "district": "开化县",
    "year_2018": 2128,
    "year_2017": 2134,
    "year_2016": 2003,
    "year_2015": 2073,
    "year_2014": 1937,
    "year_2013": 1490,
    "year_2012": 1570,
    "year_2011": 1274,
    "year_2010": 1417,
    "year_2009": 1593,
    "year_2008": 1623,
    "year_2007": 1699,
    "year_2006": 1446,
    "year_2005": 1651,
    "year_2004": 53,
    "year_2003": 1383,
    "year_2002": "-",
    "year_2001": "-"
  },
  {
    "ID": 52,
    "urban": "衢州市",
    "district": "龙游县",
    "year_2018": 3663,
    "year_2017": 3084,
    "year_2016": 2593,
    "year_2015": 2502,
    "year_2014": 2294,
    "year_2013": 2290,
    "year_2012": 2701,
    "year_2011": 2780,
    "year_2010": 2495,
    "year_2009": 2508,
    "year_2008": 2478,
    "year_2007": 2867,
    "year_2006": 2803,
    "year_2005": 2783,
    "year_2004": 12,
    "year_2003": 2536,
    "year_2002": "-",
    "year_2001": "-"
  },
  {
    "ID": 53,
    "urban": "衢州市",
    "district": "衢州市",
    "year_2018": 8900,
    "year_2017": 8257,
    "year_2016": 7509,
    "year_2015": 7444,
    "year_2014": 6904,
    "year_2013": 6012,
    "year_2012": 6523,
    "year_2011": 6136,
    "year_2010": 5891,
    "year_2009": 6983,
    "year_2008": 6874,
    "year_2007": 7235,
    "year_2006": 6853,
    "year_2005": 6834,
    "year_2004": 869,
    "year_2003": 6115,
    "year_2002": "-",
    "year_2001": "-"
  },
  {
    "ID": 54,
    "urban": "金华市",
    "district": "金华市区",
    "year_2018": 2170,
    "year_2017": 1716,
    "year_2016": 1849,
    "year_2015": 1797,
    "year_2014": 2928,
    "year_2013": 3378,
    "year_2012": 3888,
    "year_2011": 3282,
    "year_2010": 2533,
    "year_2009": 3405,
    "year_2008": 3034,
    "year_2007": 2915,
    "year_2006": 3186,
    "year_2005": 3389,
    "year_2004": 3648,
    "year_2003": 3627,
    "year_2002": 4350,
    "year_2001": 4432
  },
  {
    "ID": 55,
    "urban": "金华市",
    "district": "东阳市",
    "year_2018": 2049,
    "year_2017": 1447,
    "year_2016": 1399,
    "year_2015": 1457,
    "year_2014": 1325,
    "year_2013": 1272,
    "year_2012": 1316,
    "year_2011": 1381,
    "year_2010": 1133,
    "year_2009": 2172,
    "year_2008": 2087,
    "year_2007": 2351,
    "year_2006": 2217,
    "year_2005": 2272,
    "year_2004": 2197,
    "year_2003": 1993,
    "year_2002": 2021,
    "year_2001": 2221
  },
  {
    "ID": 56,
    "urban": "金华市",
    "district": "义乌市",
    "year_2018": 844,
    "year_2017": 885,
    "year_2016": 998,
    "year_2015": 1030,
    "year_2014": 1104,
    "year_2013": 995,
    "year_2012": 960,
    "year_2011": 1064,
    "year_2010": 1084,
    "year_2009": 1142,
    "year_2008": 1050,
    "year_2007": 1335,
    "year_2006": 1508,
    "year_2005": 1391,
    "year_2004": 1118,
    "year_2003": 1046,
    "year_2002": 1086,
    "year_2001": 974
  },
  {
    "ID": 57,
    "urban": "金华市",
    "district": "武义县",
    "year_2018": 13255,
    "year_2017": 12788,
    "year_2016": 12205,
    "year_2015": 12221,
    "year_2014": 11979,
    "year_2013": 10766,
    "year_2012": 9432,
    "year_2011": 8319,
    "year_2010": 7424,
    "year_2009": 7523,
    "year_2008": 7084,
    "year_2007": 6580,
    "year_2006": 6532,
    "year_2005": 6088,
    "year_2004": 5512,
    "year_2003": 5493,
    "year_2002": 5980,
    "year_2001": 5125
  },
  {
    "ID": 58,
    "urban": "金华市",
    "district": "浦江县",
    "year_2018": 1055,
    "year_2017": 1057,
    "year_2016": 1137,
    "year_2015": 1151,
    "year_2014": 1174,
    "year_2013": 1147,
    "year_2012": 1164,
    "year_2011": 1208,
    "year_2010": 1147,
    "year_2009": 1149,
    "year_2008": 1278,
    "year_2007": 1285,
    "year_2006": 1258,
    "year_2005": 1270,
    "year_2004": 1269,
    "year_2003": 1292,
    "year_2002": 1240,
    "year_2001": 1408
  },
  {
    "ID": 59,
    "urban": "金华市",
    "district": "兰溪市",
    "year_2018": 1798,
    "year_2017": 1807,
    "year_2016": 1792,
    "year_2015": 1797,
    "year_2014": 1366,
    "year_2013": 1223,
    "year_2012": 1349,
    "year_2011": 1248,
    "year_2010": 1243,
    "year_2009": 1234,
    "year_2008": 1254,
    "year_2007": 1249,
    "year_2006": 1245,
    "year_2005": 1333,
    "year_2004": 1183,
    "year_2003": 1219,
    "year_2002": 1111,
    "year_2001": 1095
  },
  {
    "ID": 60,
    "urban": "金华市",
    "district": "磐安县",
    "year_2018": 2219,
    "year_2017": 2236,
    "year_2016": 2179,
    "year_2015": 2422,
    "year_2014": 2221,
    "year_2013": 2096,
    "year_2012": 2202,
    "year_2011": 2159,
    "year_2010": 2004,
    "year_2009": 2048,
    "year_2008": 1759,
    "year_2007": 1995,
    "year_2006": 1848,
    "year_2005": 1556,
    "year_2004": 1533,
    "year_2003": 1564,
    "year_2002": 1554,
    "year_2001": 1563
  },
  {
    "ID": 61,
    "urban": "金华市",
    "district": "永康市",
    "year_2018": 14,
    "year_2017": 15,
    "year_2016": 21,
    "year_2015": 22,
    "year_2014": 12,
    "year_2013": 23,
    "year_2012": 25,
    "year_2011": 28,
    "year_2010": 62,
    "year_2009": 76,
    "year_2008": 70,
    "year_2007": 188,
    "year_2006": 259,
    "year_2005": 253,
    "year_2004": 240,
    "year_2003": 219,
    "year_2002": 295,
    "year_2001": 322
  },
  {
    "ID": 62,
    "urban": "金华市",
    "district": "金华市",
    "year_2018": 23404,
    "year_2017": 21951,
    "year_2016": 21580,
    "year_2015": 21897,
    "year_2014": 22109,
    "year_2013": 20900,
    "year_2012": 20336,
    "year_2011": 18689,
    "year_2010": 16630,
    "year_2009": 18749,
    "year_2008": 17616,
    "year_2007": 17898,
    "year_2006": 18053,
    "year_2005": 17552,
    "year_2004": 16700,
    "year_2003": 16453,
    "year_2002": 17637,
    "year_2001": 17140
  },
  {
    "ID": 63,
    "urban": "丽水市",
    "district": "松阳县",
    "year_2018": 13020,
    "year_2017": 12438,
    "year_2016": 11913,
    "year_2015": 11326,
    "year_2014": 11271,
    "year_2013": 10959,
    "year_2012": 10603,
    "year_2011": 9525,
    "year_2010": 9050,
    "year_2009": 8725,
    "year_2008": 7285,
    "year_2007": 6388,
    "year_2006": 5688,
    "year_2005": 5195,
    "year_2004": 4758,
    "year_2003": 4306,
    "year_2002": 3633,
    "year_2001": 2776
  },
  {
    "ID": 64,
    "urban": "丽水市",
    "district": "云和县",
    "year_2018": 1196,
    "year_2017": 1135,
    "year_2016": 907,
    "year_2015": 872,
    "year_2014": 826,
    "year_2013": 870,
    "year_2012": 873,
    "year_2011": 803,
    "year_2010": 691,
    "year_2009": 712,
    "year_2008": 577,
    "year_2007": 337,
    "year_2006": 257,
    "year_2005": 217,
    "year_2004": 192,
    "year_2003": 175,
    "year_2002": 160,
    "year_2001": 149
  },
  {
    "ID": 65,
    "urban": "丽水市",
    "district": "庆元县",
    "year_2018": 531,
    "year_2017": 536,
    "year_2016": 521,
    "year_2015": 519,
    "year_2014": 528,
    "year_2013": 521,
    "year_2012": 505,
    "year_2011": 587,
    "year_2010": 554,
    "year_2009": 557,
    "year_2008": 520,
    "year_2007": 504,
    "year_2006": 488,
    "year_2005": 505,
    "year_2004": 462,
    "year_2003": 443,
    "year_2002": 444,
    "year_2001": 426
  },
  {
    "ID": 66,
    "urban": "丽水市",
    "district": "景宁畲族自治县",
    "year_2018": 2179,
    "year_2017": 2348,
    "year_2016": 2225,
    "year_2015": 2402,
    "year_2014": 2389,
    "year_2013": 2248,
    "year_2012": 1860,
    "year_2011": 1449,
    "year_2010": 663,
    "year_2009": 599,
    "year_2008": 552,
    "year_2007": 508,
    "year_2006": 531,
    "year_2005": 504,
    "year_2004": 475,
    "year_2003": 462,
    "year_2002": 465,
    "year_2001": 432
  },
  {
    "ID": 67,
    "urban": "丽水市",
    "district": "青田县",
    "year_2018": 307,
    "year_2017": 252,
    "year_2016": 195,
    "year_2015": 187,
    "year_2014": 181,
    "year_2013": 182,
    "year_2012": 171,
    "year_2011": 159,
    "year_2010": 155,
    "year_2009": 150,
    "year_2008": 155,
    "year_2007": 136,
    "year_2006": 115,
    "year_2005": 144,
    "year_2004": 134,
    "year_2003": 127,
    "year_2002": 116,
    "year_2001": 114
  },
  {
    "ID": 68,
    "urban": "丽水市",
    "district": "缙云县",
    "year_2018": 2300,
    "year_2017": 2228,
    "year_2016": 2175,
    "year_2015": 2171,
    "year_2014": 2078,
    "year_2013": 2018,
    "year_2012": 2302,
    "year_2011": 2176,
    "year_2010": 2009,
    "year_2009": 2135,
    "year_2008": 2014,
    "year_2007": 1989,
    "year_2006": 1797,
    "year_2005": 1653,
    "year_2004": 1609,
    "year_2003": 1343,
    "year_2002": 1186,
    "year_2001": 936
  },
  {
    "ID": 69,
    "urban": "丽水市",
    "district": "遂昌县",
    "year_2018": 11793,
    "year_2017": 10963,
    "year_2016": 9951,
    "year_2015": 9509,
    "year_2014": 9193,
    "year_2013": 7548,
    "year_2012": 7632,
    "year_2011": 7306,
    "year_2010": 6819,
    "year_2009": 6448,
    "year_2008": 5819,
    "year_2007": 5464,
    "year_2006": 4815,
    "year_2005": 4343,
    "year_2004": 3825,
    "year_2003": 3362,
    "year_2002": 2852,
    "year_2001": 2243
  },
  {
    "ID": 70,
    "urban": "丽水市",
    "district": "龙泉市",
    "year_2018": 2070,
    "year_2017": 2000,
    "year_2016": 1894,
    "year_2015": 1830,
    "year_2014": 1713,
    "year_2013": 1568,
    "year_2012": 1410,
    "year_2011": 1337,
    "year_2010": 1239,
    "year_2009": 1162,
    "year_2008": 1094,
    "year_2007": 1037,
    "year_2006": 694,
    "year_2005": 734,
    "year_2004": 701,
    "year_2003": 681,
    "year_2002": 743,
    "year_2001": 705
  },
  {
    "ID": 71,
    "urban": "丽水市",
    "district": "莲都区",
    "year_2018": 1877,
    "year_2017": 1936,
    "year_2016": 1838,
    "year_2015": 1738,
    "year_2014": 1734,
    "year_2013": 1672,
    "year_2012": 1795,
    "year_2011": 1590,
    "year_2010": 1447,
    "year_2009": 1412,
    "year_2008": 1281,
    "year_2007": 1128,
    "year_2006": 865,
    "year_2005": 798,
    "year_2004": 833,
    "year_2003": 758,
    "year_2002": 662,
    "year_2001": 432
  },
  {
    "ID": 72,
    "urban": "丽水市",
    "district": "丽水市",
    "year_2018": 35273,
    "year_2017": 33836,
    "year_2016": 31619,
    "year_2015": 30554,
    "year_2014": 29913,
    "year_2013": 27586,
    "year_2012": 27151,
    "year_2011": 24932,
    "year_2010": 22627,
    "year_2009": 21900,
    "year_2008": 19297,
    "year_2007": 17491,
    "year_2006": 15250,
    "year_2005": 14093,
    "year_2004": 12989,
    "year_2003": 11657,
    "year_2002": 10261,
    "year_2001": 8213
  },
  {
    "ID": 73,
    "urban": "杭州市",
    "district": "下城区",
    "year_2018": 129,
    "year_2017": 134,
    "year_2016": 126,
    "year_2015": "-",
    "year_2014": "-",
    "year_2013": "-",
    "year_2012": "-",
    "year_2011": "-",
    "year_2010": "-",
    "year_2009": "-",
    "year_2008": "-",
    "year_2007": "-",
    "year_2006": "-",
    "year_2005": "-",
    "year_2004": "-",
    "year_2003": "-",
    "year_2002": "-",
    "year_2001": "-"
  },
  {
    "ID": 74,
    "urban": "杭州市",
    "district": "富阳区",
    "year_2018": 6777,
    "year_2017": 7018,
    "year_2016": 6469,
    "year_2015": 6827,
    "year_2014": 5863,
    "year_2013": 6610,
    "year_2012": 6116,
    "year_2011": 5659,
    "year_2010": 5039,
    "year_2009": 4983,
    "year_2008": 4808,
    "year_2007": 3890,
    "year_2006": 3340,
    "year_2005": 2935,
    "year_2004": 2628,
    "year_2003": 2183,
    "year_2002": 2394,
    "year_2001": 2326
  },
  {
    "ID": 75,
    "urban": "杭州市",
    "district": "滨江区",
    "year_2018": 18,
    "year_2017": 8,
    "year_2016": 8,
    "year_2015": 9,
    "year_2014": 8,
    "year_2013": 10,
    "year_2012": 15,
    "year_2011": 36,
    "year_2010": 65,
    "year_2009": 97,
    "year_2008": 100,
    "year_2007": 104,
    "year_2006": 94,
    "year_2005": 98,
    "year_2004": 102,
    "year_2003": 67,
    "year_2002": 58,
    "year_2001": 60
  },
  {
    "ID": 76,
    "urban": "杭州市",
    "district": "建德市",
    "year_2018": 3095,
    "year_2017": 2852,
    "year_2016": 2617,
    "year_2015": 2398,
    "year_2014": 2328,
    "year_2013": 2852,
    "year_2012": 2766,
    "year_2011": 3153,
    "year_2010": 3681,
    "year_2009": 3506,
    "year_2008": 3744,
    "year_2007": 3736,
    "year_2006": 3676,
    "year_2005": 3337,
    "year_2004": 3123,
    "year_2003": 2767,
    "year_2002": 2918,
    "year_2001": 2585
  },
  {
    "ID": 77,
    "urban": "杭州市",
    "district": "拱墅区",
    "year_2018": "-",
    "year_2017": "-",
    "year_2016": "-",
    "year_2015": "-",
    "year_2014": "-",
    "year_2013": "-",
    "year_2012": "-",
    "year_2011": "-",
    "year_2010": "-",
    "year_2009": "-",
    "year_2008": "-",
    "year_2007": "-",
    "year_2006": "-",
    "year_2005": "-",
    "year_2004": "-",
    "year_2003": "-",
    "year_2002": "-",
    "year_2001": "-"
  },
  {
    "ID": 78,
    "urban": "杭州市",
    "district": "江干区",
    "year_2018": "-",
    "year_2017": "-",
    "year_2016": "-",
    "year_2015": "-",
    "year_2014": "-",
    "year_2013": "-",
    "year_2012": "-",
    "year_2011": "-",
    "year_2010": "-",
    "year_2009": "-",
    "year_2008": "-",
    "year_2007": "-",
    "year_2006": "-",
    "year_2005": "-",
    "year_2004": "-",
    "year_2003": "-",
    "year_2002": "-",
    "year_2001": "-"
  },
  {
    "ID": 79,
    "urban": "杭州市",
    "district": "西湖区",
    "year_2018": 453,
    "year_2017": 450,
    "year_2016": 410,
    "year_2015": 407,
    "year_2014": 487,
    "year_2013": 438,
    "year_2012": 496,
    "year_2011": 515,
    "year_2010": 529,
    "year_2009": 580,
    "year_2008": 597,
    "year_2007": 658,
    "year_2006": 668,
    "year_2005": 697,
    "year_2004": 789,
    "year_2003": 752,
    "year_2002": 872,
    "year_2001": 987
  },
  {
    "ID": 80,
    "urban": "杭州市",
    "district": "临安区",
    "year_2018": 2531,
    "year_2017": 2546,
    "year_2016": 2409,
    "year_2015": 2540,
    "year_2014": 2500,
    "year_2013": 2472,
    "year_2012": 2338,
    "year_2011": 2002,
    "year_2010": 1945,
    "year_2009": 2112,
    "year_2008": 2101,
    "year_2007": 2132,
    "year_2006": 2056,
    "year_2005": 2090,
    "year_2004": 1964,
    "year_2003": 2096,
    "year_2002": 2394,
    "year_2001": 2563
  },
  {
    "ID": 81,
    "urban": "杭州市",
    "district": "余杭区",
    "year_2018": 8324,
    "year_2017": 8512,
    "year_2016": 8056,
    "year_2015": 7952,
    "year_2014": 7867,
    "year_2013": 6830,
    "year_2012": 10316,
    "year_2011": 9949,
    "year_2010": 9614,
    "year_2009": 9378,
    "year_2008": 9106,
    "year_2007": 8884,
    "year_2006": 8888,
    "year_2005": 8408,
    "year_2004": 7441,
    "year_2003": 6781,
    "year_2002": 5913,
    "year_2001": 5573
  },
  {
    "ID": 82,
    "urban": "杭州市",
    "district": "上城区",
    "year_2018": "-",
    "year_2017": "-",
    "year_2016": "-",
    "year_2015": "-",
    "year_2014": "-",
    "year_2013": "-",
    "year_2012": "-",
    "year_2011": "-",
    "year_2010": "-",
    "year_2009": "-",
    "year_2008": "-",
    "year_2007": "-",
    "year_2006": "-",
    "year_2005": "-",
    "year_2004": "-",
    "year_2003": "-",
    "year_2002": "-",
    "year_2001": "-"
  },
  {
    "ID": 83,
    "urban": "杭州市",
    "district": "淳安县",
    "year_2018": 4675,
    "year_2017": 4591,
    "year_2016": 4366,
    "year_2015": 4523,
    "year_2014": 4254,
    "year_2013": 6525,
    "year_2012": 7354,
    "year_2011": 7132,
    "year_2010": 6850,
    "year_2009": 6753,
    "year_2008": 6447,
    "year_2007": 6122,
    "year_2006": 5682,
    "year_2005": 5461,
    "year_2004": 6422,
    "year_2003": 7800,
    "year_2002": 8665,
    "year_2001": 8284
  },
  {
    "ID": 84,
    "urban": "杭州市",
    "district": "萧山区",
    "year_2018": 618,
    "year_2017": 600,
    "year_2016": 585,
    "year_2015": 573,
    "year_2014": 509,
    "year_2013": 876,
    "year_2012": 882,
    "year_2011": 891,
    "year_2010": 890,
    "year_2009": 885,
    "year_2008": 863,
    "year_2007": 842,
    "year_2006": 825,
    "year_2005": 802,
    "year_2004": 852,
    "year_2003": 811,
    "year_2002": 781,
    "year_2001": 812
  },
  {
    "ID": 85,
    "urban": "杭州市",
    "district": "桐庐县",
    "year_2018": 3466,
    "year_2017": 3387,
    "year_2016": 3096,
    "year_2015": 2750,
    "year_2014": 2599,
    "year_2013": 1753,
    "year_2012": 1814,
    "year_2011": 1835,
    "year_2010": 1651,
    "year_2009": 1653,
    "year_2008": 1593,
    "year_2007": 1571,
    "year_2006": 1455,
    "year_2005": 1467,
    "year_2004": 1498,
    "year_2003": 1538,
    "year_2002": 1396,
    "year_2001": 1508
  },
  {
    "ID": 86,
    "urban": "杭州市",
    "district": "杭州市",
    "year_2018": 30086,
    "year_2017": 30098,
    "year_2016": 28142,
    "year_2015": 27979,
    "year_2014": 26415,
    "year_2013": 28366,
    "year_2012": 32097,
    "year_2011": 31172,
    "year_2010": 30264,
    "year_2009": 29947,
    "year_2008": 29359,
    "year_2007": 27939,
    "year_2006": 26684,
    "year_2005": 25295,
    "year_2004": 24819,
    "year_2003": 24795,
    "year_2002": 25391,
    "year_2001": 24698
  },
  {
    "ID": 87,
    "urban": "绍兴市",
    "district": "新昌县",
    "year_2018": 5277,
    "year_2017": 5720,
    "year_2016": 5886,
    "year_2015": 5870,
    "year_2014": 5794,
    "year_2013": 5645,
    "year_2012": 5998,
    "year_2011": 5963,
    "year_2010": 5925,
    "year_2009": 6154,
    "year_2008": 6016,
    "year_2007": 5898,
    "year_2006": 5670,
    "year_2005": 5634,
    "year_2004": 5542,
    "year_2003": 5461,
    "year_2002": 5159,
    "year_2001": 5064
  },
  {
    "ID": 88,
    "urban": "绍兴市",
    "district": "嵊州市",
    "year_2018": 17394,
    "year_2017": 18377,
    "year_2016": 18154,
    "year_2015": 19359,
    "year_2014": 20229,
    "year_2013": 19867,
    "year_2012": 20601,
    "year_2011": 19710,
    "year_2010": 19138,
    "year_2009": 18554,
    "year_2008": 17904,
    "year_2007": 17406,
    "year_2006": 16991,
    "year_2005": 15098,
    "year_2004": 14837,
    "year_2003": 11592,
    "year_2002": 12261,
    "year_2001": 9516
  },
  {
    "ID": 89,
    "urban": "绍兴市",
    "district": "诸暨市",
    "year_2018": 8043,
    "year_2017": 12957,
    "year_2016": 12730,
    "year_2015": 12430,
    "year_2014": 5779,
    "year_2013": 12175,
    "year_2012": 12501,
    "year_2011": 12400,
    "year_2010": 12266,
    "year_2009": 12282,
    "year_2008": 11903,
    "year_2007": 11777,
    "year_2006": 10694,
    "year_2005": 9492,
    "year_2004": 9267,
    "year_2003": 9540,
    "year_2002": 8822,
    "year_2001": 6935
  },
  {
    "ID": 90,
    "urban": "绍兴市",
    "district": "越城区",
    "year_2018": 759,
    "year_2017": 781,
    "year_2016": 792,
    "year_2015": 1219,
    "year_2014": 1117,
    "year_2013": 440,
    "year_2012": 430,
    "year_2011": 422,
    "year_2010": 480,
    "year_2009": 510,
    "year_2008": 393,
    "year_2007": 397,
    "year_2006": 545,
    "year_2005": 665,
    "year_2004": 670,
    "year_2003": 755,
    "year_2002": 765,
    "year_2001": 846
  },
  {
    "ID": 91,
    "urban": "绍兴市",
    "district": "柯桥区",
    "year_2018": 7523,
    "year_2017": 7295,
    "year_2016": 7183,
    "year_2015": 7172,
    "year_2014": 7400,
    "year_2013": 8766,
    "year_2012": 8797,
    "year_2011": 8844,
    "year_2010": 8432,
    "year_2009": 9505,
    "year_2008": 8589,
    "year_2007": 9244,
    "year_2006": 9173,
    "year_2005": 9222,
    "year_2004": 8602,
    "year_2003": 8833,
    "year_2002": 7783,
    "year_2001": 7150
  },
  {
    "ID": 92,
    "urban": "绍兴市",
    "district": "上虞区",
    "year_2018": 2446,
    "year_2017": 2795,
    "year_2016": 2557,
    "year_2015": 2485,
    "year_2014": 2950,
    "year_2013": 2817,
    "year_2012": 2992,
    "year_2011": 2968,
    "year_2010": 3339,
    "year_2009": 3286,
    "year_2008": 3376,
    "year_2007": 3305,
    "year_2006": 3511,
    "year_2005": 3304,
    "year_2004": 2922,
    "year_2003": 2944,
    "year_2002": 2631,
    "year_2001": 2483
  },
  {
    "ID": 93,
    "urban": "绍兴市",
    "district": "绍兴市",
    "year_2018": 41442,
    "year_2017": 47925,
    "year_2016": 47302,
    "year_2015": 48535,
    "year_2014": 43269,
    "year_2013": 49710,
    "year_2012": 51319,
    "year_2011": 50307,
    "year_2010": 49580,
    "year_2009": 50291,
    "year_2008": 48181,
    "year_2007": 48027,
    "year_2006": 46584,
    "year_2005": 43415,
    "year_2004": 41840,
    "year_2003": 39125,
    "year_2002": 37421,
    "year_2001": 31994
  },
  {
    "ID": 94,
    "urban": "湖州市",
    "district": "安吉县",
    "year_2018": 3916,
    "year_2017": 3977,
    "year_2016": 4305,
    "year_2015": 4298,
    "year_2014": 4311,
    "year_2013": 4452,
    "year_2012": 4414,
    "year_2011": 4265,
    "year_2010": 4477,
    "year_2009": 4585,
    "year_2008": 4691,
    "year_2007": 4310,
    "year_2006": 4479,
    "year_2005": 4408,
    "year_2004": 4703,
    "year_2003": 4081,
    "year_2002": 3726,
    "year_2001": 3476
  },
  {
    "ID": 95,
    "urban": "湖州市",
    "district": "长兴县",
    "year_2018": 5044,
    "year_2017": 5018,
    "year_2016": 4503,
    "year_2015": 4756,
    "year_2014": 4540,
    "year_2013": 4363,
    "year_2012": 4517,
    "year_2011": 4562,
    "year_2010": 4160,
    "year_2009": 4498,
    "year_2008": 4431,
    "year_2007": 3761,
    "year_2006": 2836,
    "year_2005": 2558,
    "year_2004": 2669,
    "year_2003": 2543,
    "year_2002": 2412,
    "year_2001": 2316
  },
  {
    "ID": 96,
    "urban": "湖州市",
    "district": "德清县",
    "year_2018": 1382,
    "year_2017": 1365,
    "year_2016": 1291,
    "year_2015": 1153,
    "year_2014": 1121,
    "year_2013": 1290,
    "year_2012": 1304,
    "year_2011": 1450,
    "year_2010": 1408,
    "year_2009": 1778,
    "year_2008": 1900,
    "year_2007": 1606,
    "year_2006": 1224,
    "year_2005": 1243,
    "year_2004": 1178,
    "year_2003": 1076,
    "year_2002": 1102,
    "year_2001": 1042
  },
  {
    "ID": 97,
    "urban": "湖州市",
    "district": "吴兴区",
    "year_2018": 319,
    "year_2017": 432,
    "year_2016": 440,
    "year_2015": 392,
    "year_2014": 370,
    "year_2013": 380,
    "year_2012": 372,
    "year_2011": 367,
    "year_2010": 305,
    "year_2009": 321,
    "year_2008": 363,
    "year_2007": 296,
    "year_2006": 295,
    "year_2005": 245,
    "year_2004": 276,
    "year_2003": 244,
    "year_2002": 197,
    "year_2001": 209
  },
  {
    "ID": 98,
    "urban": "湖州市",
    "district": "南浔区",
    "year_2018": "-",
    "year_2017": "-",
    "year_2016": "-",
    "year_2015": "-",
    "year_2014": "-",
    "year_2013": "-",
    "year_2012": "-",
    "year_2011": "-",
    "year_2010": "-",
    "year_2009": "-",
    "year_2008": "-",
    "year_2007": "-",
    "year_2006": "-",
    "year_2005": "-",
    "year_2004": "-",
    "year_2003": "-",
    "year_2002": "-",
    "year_2001": "-"
  },
  {
    "ID": 99,
    "urban": "湖州市",
    "district": "湖州市",
    "year_2018": 10661,
    "year_2017": 10792,
    "year_2016": 10539,
    "year_2015": 10599,
    "year_2014": 10342,
    "year_2013": 10485,
    "year_2012": 10607,
    "year_2011": 10644,
    "year_2010": 10350,
    "year_2009": 11182,
    "year_2008": 11385,
    "year_2007": 9973,
    "year_2006": 8834,
    "year_2005": 8454,
    "year_2004": 8826,
    "year_2003": 7944,
    "year_2002": 7437,
    "year_2001": 7043
  }
]